MANIFEST.in
README.rst
setup.py
docs/HISTORY.txt
docs/LICENSE.GPL
docs/LICENSE.txt
plonetheme/__init__.py
plonetheme.aqueouslight.egg-info/PKG-INFO
plonetheme.aqueouslight.egg-info/SOURCES.txt
plonetheme.aqueouslight.egg-info/dependency_links.txt
plonetheme.aqueouslight.egg-info/entry_points.txt
plonetheme.aqueouslight.egg-info/namespace_packages.txt
plonetheme.aqueouslight.egg-info/not-zip-safe
plonetheme.aqueouslight.egg-info/requires.txt
plonetheme.aqueouslight.egg-info/top_level.txt
plonetheme/aqueouslight/__init__.py
plonetheme/aqueouslight/configure.zcml
plonetheme/aqueouslight/profiles/default/metadata.xml
plonetheme/aqueouslight/profiles/default/theme.xml
plonetheme/aqueouslight/static/index.html
plonetheme/aqueouslight/static/manifest.cfg
plonetheme/aqueouslight/static/rules.xml
plonetheme/aqueouslight/static/css/styles.css
plonetheme/aqueouslight/static/images/body.jpg
plonetheme/aqueouslight/static/images/content.jpg
plonetheme/aqueouslight/static/images/innerwrapper.jpg
plonetheme/aqueouslight/static/images/nav.jpg
plonetheme/aqueouslight/static/images/sidebarh2.jpg
plonetheme/aqueouslight/static/images/sidebarright.jpg