Metadata-Version: 1.1
Name: plonetheme.aqueouslight
Version: 1.0
Summary: An installable Diazo theme for Plone 4.1
Home-page: http://stxnext.pl
Author: STX Next Sp. z o.o, Sebastian Kalinowski
Author-email: info@stxnext.pl
License: gpl
Keywords: python plone diazo theme
Platform: UNKNOWN
Classifier: Programming Language :: Python
Classifier: Framework :: Plone
